<xml>
    <item>
        <title>E.T. the Extra-Terrestrial (1982)</title>
        <meta>
            <imdb>tt0083866</imdb>
            <content>movie</content>
            <title>E.T. the Extra-Terrestrial</title>
            <year>1982</year>
        </meta>
        <link>
            <sublink name="[B][COLOR gold] 720p [/COLOR][/B]">https://real-debrid.com/d/AXPFC4ATRSBFC</sublink>
            <sublink name="[B][COLOR gold] 720p [/COLOR][/B]">https://real-debrid.com/d/PVAFG6V2LZ2P4</sublink>
        </link>
    </item>

    <item>
        <title>Halloween III: Season of the Witch (1982)</title>
        <meta>
            <imdb>tt0085636</imdb>
            <content>movie</content>
            <title>Halloween III: Season of the Witch</title>
            <year>1982</year>
        </meta>
        <link>
            <sublink name="[B][COLOR gold] 1080p [/COLOR][/B]">https://real-debrid.com/d/7HNY76GMA6UBA</sublink>
            <sublink name="[B][COLOR gold] 720p [/COLOR][/B]">https://real-debrid.com/d/NZORYP2XDUKW4</sublink>
        </link>
    </item>

    <item>
        <title>Rambo - First Blood 4k (1982)</title>
        <meta>
            <imdb>tt0083944</imdb>
            <content>movie</content>
            <title>Rambo - First Blood</title>
            <year>1982</year>
        </meta>
        <link>
            <sublink name="[B][COLOR gold] 4k [/COLOR][/B]">https://real-debrid.com/d/O6VBZKKSHNRAC</sublink>
        </link>
    </item>
</xml>