<xml>
    <item>
        <title>Beauty and the Beast: The Enchanted Christmas</title>
        <meta>
            <imdb>tt0118692</imdb>
            <content>movie</content>
            <title>Beauty and the Beast: The Enchanted Christmas</title>
            <year>1997</year>
        </meta>
        <link>
            <sublink name="[B][COLOR gold] 720p [/COLOR][/B]">https://real-debrid.com/d/2BIU2ZCMJYYQ2</sublink>
        </link>
    </item>

    <item>
        <title>Contact</title>
        <meta>
            <imdb>tt0118884</imdb>
            <content>movie</content>
            <title>Contacts</title>
            <year>1997</year>
        </meta>
        <link>
            <sublink name="[B][COLOR gold] 720p [/COLOR][/B]">https://real-debrid.com/d/XVUXT2HQJVQPE</sublink>
        </link>
    </item>

    <item>
        <title>Home Alone 3</title>
        <meta>
            <imdb>tt0119303</imdb>
            <content>movie</content>
            <title>Home Alone 3</title>
            <year>1997</year>
        </meta>
        <link>
            <sublink name="[B][COLOR gold] 1080p [/COLOR][/B]">https://real-debrid.com/d/DOP7ZFAFWU74W</sublink>
        </link>
    </item>

    <item>
        <title>The Lost World: Jurassic Park</title>
        <meta>
            <imdb>tt0119567</imdb>
            <content>movie</content>
            <title>The Lost World: Jurassic Park</title>
            <year>1997</year>
        </meta>
        <link>
            <sublink name="[B][COLOR gold] 1080p [/COLOR][/B]">https://real-debrid.com/d/UA2TFXMJS4LQK</sublink>
        </link>
    </item>

    <item>
        <title>My Best Friend's Wedding</title>
        <meta>
            <imdb>tt0119738</imdb>
            <content>movie</content>
            <title>My Best Friend's Wedding</title>
            <year>1997</year>
        </meta>
        <link>
            <sublink name="[B][COLOR gold] 720p [/COLOR][/B]">https://real-debrid.com/d/QYLCAD4BZCSF6</sublink>
        </link>
    </item>

    <item>
        <title>RocketMan</title>
        <meta>
            <imdb>tt0120029</imdb>
            <content>movie</content>
            <title>RocketMan</title>
            <year>1997</year>
        </meta>
        <link>
            <sublink name="[B][COLOR gold] 720p [/COLOR][/B]">https://real-debrid.com/d/MO7QRVFXNIQWQ</sublink>
        </link>
    </item>
</xml>