<xml>
    <item>
        <title>16 Wishes</title>
        <meta>
            <imdb>tt1646876</imdb>
            <content>movie</content>
            <title>16 Wishes</title>
            <year>2010</year>
        </meta>
        <link>https://real-debrid.com/d/RQOQYU2VR3WY6</link>
        <thumbnail>https://image.tmdb.org/t/p/w220_and_h330_face/ej5vw4lbGdG8V5lbkP6mgXA6EcT.jpg</thumbnail>
        <fanart>https://image.tmdb.org/t/p/w500_and_h282_face/cj0pBleq7DEbj6Z5jKG8Cfwptft.jpg</fanart>
    </item>

    <item>
        <title>The Search for Santa Paws</title>
        <meta>
            <imdb>tt1544572</imdb>
            <content>movie</content>
            <title>The Search for Santa Paws</title>
            <year>2010</year>
        </meta>
        <link>
            <sublink name="[B][COLOR gold] 1080p [/COLOR][/B]">https://real-debrid.com/d/F4ZMQK4E5O6VE</sublink>
            <sublink name="[B][COLOR gold] 720p [/COLOR][/B]">https://real-debrid.com/d/XDZMEXHQRDQ5U</sublink>
        </link>
        <thumbnail>https://image.tmdb.org/t/p/w220_and_h330_face/smxA8yvZ0LzDPer9BIRd4pyOpx1.jpg</thumbnail>
        <fanart>https://image.tmdb.org/t/p/w500_and_h282_face/gOXpeTvSDPlUyrQRtWhAl3WYHIp.jpg</fanart>
    </item>

    <item>
        <title>Shutter Island 2010</title>
        <meta>
            <imdb>tt1130884</imdb>
            <content>movie</content>
            <title>Shutter Island</title>
            <year>2010</year>
        </meta>
        <link>
            <sublink name="[B][COLOR gold] 4k [/COLOR][/B]">https://real-debrid.com/d/YFIQRKNXPB4RI</sublink>
        </link>
        <thumbnail></thumbnail>
        <fanart></fanart>
    </item>
</xml>