<xml>
    <item>
        <title>Santa Paws 2: The Santa Pups 2012</title>
        <meta>
            <imdb>tt1544572</imdb>
            <content>movie</content>
            <title>Santa Paws 2: The Santa Pups</title>
            <year>2012</year>
        </meta>
        <link>
            <sublink name="[B][COLOR gold] 1080p [/COLOR][/B]">https://real-debrid.com/d/NG6IZ2EWLPVPS</sublink>
        </link>
        <thumbnail>https://image.tmdb.org/t/p/w220_and_h330_face/g5uCvSkbug9PQTtbkiCKUMzKq3Z.jpg</thumbnail>
        <fanart>https://image.tmdb.org/t/p/w500_and_h282_face/uqdp0h8Se2gPKLB2axVs7KI1ppL.jpg</fanart>
    </item>

    <item>
        <title>The Search for Santa Paws 2010</title>
        <meta>
            <imdb>tt1544572</imdb>
            <content>movie</content>
            <title>The Search for Santa Paws</title>
            <year>2010</year>
        </meta>
        <link>
            <sublink name="[B][COLOR gold] 1080p [/COLOR][/B]">https://real-debrid.com/d/F4ZMQK4E5O6VE</sublink>
            <sublink name="[B][COLOR gold] 720p [/COLOR][/B]">https://real-debrid.com/d/XDZMEXHQRDQ5U</sublink>
        </link>
        <thumbnail>https://image.tmdb.org/t/p/w220_and_h330_face/smxA8yvZ0LzDPer9BIRd4pyOpx1.jpg</thumbnail>
        <fanart>https://image.tmdb.org/t/p/w500_and_h282_face/gOXpeTvSDPlUyrQRtWhAl3WYHIp.jpg</fanart>
    </item>

    <item>
        <title>Schindlers List 1993</title>
        <meta>
            <imdb>tt0108052</imdb>
            <content>movie</content>
            <title>Schindlers List</title>
            <year>1993</year>
        </meta>
        <link>
            <sublink name="[B][COLOR gold] 4k [/COLOR][/B]">https://real-debrid.com/d/QXXBKGHYW7ZRW</sublink>
        </link>
        <thumbnail></thumbnail>
        <fanart></fanart>
    </item>

    <item>
        <title>Shutter Island 2010</title>
        <meta>
            <imdb>tt1130884</imdb>
            <content>movie</content>
            <title>Shutter Island</title>
            <year>2010</year>
        </meta>
        <link>
            <sublink name="[B][COLOR gold] 4k [/COLOR][/B]">https://real-debrid.com/d/YFIQRKNXPB4RI</sublink>
        </link>
        <thumbnail></thumbnail>
        <fanart></fanart>
    </item>

    <item>
        <title>Spaceballs 1987</title>
        <meta>
            <imdb>tt0094012</imdb>
            <content>movie</content>
            <title>Spaceballs</title>
            <year>1987</year>
        </meta>
        <link>
            <sublink name="[B][COLOR gold] 4k [/COLOR][/B]">https://real-debrid.com/d/N63EUYEWCU6IW</sublink>
            <sublink name="[B][COLOR gold] 1080p [/COLOR][/B]">https://real-debrid.com/d/EG6KVFX7GWMPQ</sublink>
        </link>
        <thumbnail>https://image.tmdb.org/t/p/w220_and_h330_face/xWt9KAcToCRdJ6JH8JyZZlhkVgG.jpg</thumbnail>
        <fanart>https://image.tmdb.org/t/p/w500_and_h282_face/pZz5VmundsZO29sB3TgZKjnFEEM.jpg</fanart>
    </item>

    <item>
        <title>Star Wars: Episode VI - Return of the Jedi 1983 4k</title>
        <meta>
            <imdb>tt0094012</imdb>
            <content>movie</content>
            <title>Star Wars: Episode VI - Return of the Jedi</title>
            <year>1983</year>
        </meta>
        <link>
            <sublink name="[B][COLOR gold] 4k [/COLOR][/B]">https://real-debrid.com/d/FJREF4YO66PDK</sublink>
        </link>
        <thumbnail>https://i.imgur.com/8RfwgfX.jpg</thumbnail>
        <fanart>http://</fanart>
        <info></info>
    </item>
</xml>