<xml>
    <item>
        <title>Free Willy</title>
        <meta>
            <imdb>tt0106965</imdb>
            <content>movie</content>
            <title>Free Willy</title>
            <year>1993</year>
        </meta>
        <link>https://apicdn.vip/drive/index.php?id=I5FPAPlWNiY%2BVSWsv66HUgh8%2BtFYp1lDQ%2BSgYvCW97M6%2FSjilFqlIRHJjgp%2BH7aiMNrZsWJ5NaYLJSpFX5uixonSzJsiozgKkGjGnDlQW7ZYUEH26dKRfzmj60WLRHqjstXGNbTVYe1MdGf1AtZDlr&ref=&res=default</link>
    </item>

    <items>
        <title>Free Willy 2 - The Adventure Home (Coming Soon)</title>
        <meta>
            <imdb>tt0113114</imdb>
            <content>movie</content>
            <title>Free Willy 2 - The Adventure Home</title>
            <year>1995</year>
        </meta>
        <link></link>
    </items>

    <items>
        <title>Free Willy: Escape from Pirate's Cove (Coming Soon)</title>
        <meta>
            <imdb>tt1394329</imdb>
            <content>movie</content>
            <title>Free Willy: Escape from Pirate's Cove</title>
            <year>2010</year>
        </meta>
        <link></link>
    </items>
</xml>