<xml>
    <item>
        <title>Scary Movie</title>
        <meta>
            <imdb>ttt0175142</imdb>
            <content>movie</content>
            <title>Scary Movie</title>
            <year>2000</year>
        </meta>
        <link>https://apicdn.vip/drive/index.php?id=v5rRwAl19SjQGRkUrCZN6QtS7NWxPblL9FOyHfs53OmSgtITf0%2F%2BNkSw%2F4Md%2B6YWhQODDhfBuTUpsqUf1f7GWfOiTsR8ymvj07Lqlhqi5v3qTKsYLZ1gzfubNAq%2B5I8b2Ap21Mo1oC9OQe0tT3I5IN&ref=&res=720</link>
    </item>

    <items>
        <title>Scary Movie 2</title>
        <meta>
            <imdb>tt0257106</imdb>
            <content>movie</content>
            <title>Scary Movie 2</title>
            <year>2001</year>
        </meta>
        <link></link>
    </items>

    <items>
        <title>Scary Movie 3</title>
        <meta>
            <imdb>tt0306047</imdb>
            <content>movie</content>
            <title>Scary Movie 3</title>
            <year>2003</year>
        </meta>
        <link></link>
    </items>

    <items>
        <title>Scary Movie 4</title>
        <meta>
            <imdb>tt0362120</imdb>
            <content>movie</content>
            <title>Scary Movie 4</title>
            <year>2006</year>
        </meta>
        <link></link>
    </items>

    <item>
        <title>Scary Movie 5</title>
        <meta>
            <imdb>tt0795461</imdb>
            <content>movie</content>
            <title>Scary Movie 5</title>
            <year>2013</year>
        </meta>
        <link>https://apicdn.vip/drive/index.php?id=PWdKriBQhcQR1QRh3j0LaAA90ea362T9m%2BbNfI3yCn7ULbJrRuTuEGU2waSJMeuT4WsrFQqxHvb%2BXQJ8rsnH4qOzwkJC%2B%2Fa7KcvaeeIG6qqRIW0zp1yWnixSLmWezo006rCAg80BpLy7Xf2nAncYKRAq0EcUFQ6nGU9r7OkvuyBqw0HOWwZzUku%2FKDaLUfd8R9DIytMnJKOvxJZ14IroKf&ref=https%3A%2F%2F1watch-free.me%2Fscary-movie-5%2F&res=default</link>
    </item>
</xml>