<xml>
    <item>
        <title>4x01.Genesis</title>
        <meta>
            <tvdb>200015</tvdb>
            <content>episode</content>
        </meta>
        <link>https://apicdn.vip/drive/index.php?id=j4wWsYP3CzTVr%2BN4lp3g7g3Qc73t7d00IIqAvgJNN%2BoIewSFrL9DhUcogwW8yEop%2BUNcjxVlN%2B5hwBg5UZKycbtTgMM6eYLwlfYW2uz%2FvFp2PO98czIyEFwPFh3o8XEkLhZyK8w9BY9KLIp4wGEAZQ&ref=&res=default</link>
    </item>

    <item>
        <title>4x02.Prophets and Loss</title>
        <meta>
            <tvdb>200016</tvdb>
            <content>episode</content>
        </meta>
        <link>https://apicdn.vip/drive/index.php?id=3AI93viKCGEXF7ay2IZMCAkOVcGhYV7LsnU7CFoM65PSyaVLB4VBizR3z9E7xk9N9WiVdrwdBJioWIvYcOixvvBVHnGkBagQU2i6n8xW%2FElVP0XKsaD7ZsWgEJG5z6VehVvrxhvUFeL%2FLN38fvsonD&ref=&res=default</link>
    </item>

    <item>
        <title>4x03.Common Ground</title>
        <meta>
            <tvdb>200017</tvdb>
            <content>episode</content>
        </meta>
        <link>https://apicdn.vip/drive/index.php?id=z7sUymRotTx3Z%2BJqW72crgVB3SfNVThK0T6QTbeUemmbe9JLbgp9wsahYgx2cbPFxNemwxDLSkXDeCPz8HaSBnO%2FgqaIy2%2BZW2HmMDfi0zoVg9TvX8oGKEP8CH29zo4xbdpft4KM5uqpfhzqKUvl8N&ref=&res=default</link>
    </item>

    <item>
        <title>4x04.Virtual Slide</title>
        <meta>
            <tvdb>200018</tvdb>
            <content>episode</content>
        </meta>
        <link>https://apicdn.vip/drive/index.php?id=ynekXlhNtkw%2BVTDzkA8zGAnLIi02n7OA1Te%2BY7K4hb5LIDKdqaje%2BjWJ4VH6ZrLiUr67M%2BulsEmGmRsrpyhZxG%2FT7XjuVzYkA8Jq%2BU1ujyLDjitgiupSXMCaI7EIV6CUt%2BfSUMXMclaYi4OzrMlxq7&ref=&res=default</link>
    </item>

    <item>
        <title>4x05.World Killer</title>
        <meta>
            <tvdb>200019</tvdb>
            <content>episode</content>
        </meta>
        <link>https://apicdn.vip/drive/index.php?id=TYOrb%2FbpYx49tLzWALtGxgwfz1d1Uu0h6GVLhymAhSwysdrQRkdpFbXeQRBIg2VjYMo%2FS99mw35Mfdg1%2BypwRgLl3iASrl9huHbvdnln%2BOu3jZp9GYnQyP6yWNV5AGvH9YiKpEAhRyaGzKGE9Nck9Jm1RsehkdHdcXE6J8ygOefb%2BiaSKJ2hUHWocLOYUc5O73XoN3bvEWzUbBzCcYLu6d8TCAVyRDRvOvhqH%2F15QbnPR1HVHG64F0SC7PS4QI2RM%3D&ref=https%3A%2F%2Fakaplayer.com%2Fp2p%2FM2xSWTJyU21lYmpETy9QVnUrOFpyQT09%40tt0112167-4-5&res=default</link>
    </item>

    <item>
        <title>4x06.Oh Brother, Where Art Thou?</title>
        <meta>
            <tvdb>200020</tvdb>
            <content>episode</content>
        </meta>
        <link>https://apicdn.vip/drive/index.php?id=jftXUEeF5lRVKUYFQlVV3A1JcRee6MxThBkCLvjnrbM9AE2U4MdvL6slJR4IGbMnJwAIfMYn4rzMGgc%2BB5nS1P664Tmr82XCa%2FR6uQk%2FPoxhZXhiFxWPcTjrx4EPC9884Fx8uHv34UkeTF7cvEHQcX&ref=&res=default</link>
    </item>

    <item>
        <title>4x07.Just Say Yes</title>
        <meta>
            <tvdb>200021</tvdb>
            <content>episode</content>
        </meta>
        <link>https://apicdn.vip/drive/index.php?id=XNDbeGkJCLG2%2BB%2BA8SuuCAzIVslEHhrkZt3OuQFe%2BPWac%2F5vmF9we0TPJDSHo4hNUEkpQPb0mOHwPckLKKA1h3LvlJqFLgfASg3nJOpkYtimuS7QYiA4lwTybOUa%2Bv%2Fysv%2BKMnJoBHt2eeS9IxZkm1NEQDf32DmQbeE9HBwXtnnlc3ennQ3Lru%2FiXatRnkxpBlXDRADxuaCWgN%2F1XxGFCAtvBqCynXj3%2FqUE8QEHXOQ2gfeYEcM35V2mN33CpMo1s%3D&ref=https%3A%2F%2Fakaplayer.com%2Fp2p%2FM2xSWTJyU21lYmpETy9QVnUrOFpyQT09%40tt0112167-4-7&res=default</link>
    </item>

    <item>
        <title>4x08.The Alternateville Horror</title>
        <meta>
            <tvdb>200022</tvdb>
            <content>episode</content>
        </meta>
        <link>https://apicdn.vip/drive/index.php?id=OOFeayCiMBy3QCHPsP0LiQkxHoJjNePrksDEqqlN998Z141lfPVf4NwmAw7965y7Km7ZWHLlHOzI3K8Lj77jwvQgdJCx1YgHWcETlmgr5fbUAaB8yGChWYVmf8UMe5wJxzv%2FbzZsoWjyWRvfXETBiq&ref=&res=default</link>
    </item>

    <item>
        <title>4x09.Slidecage</title>
        <meta>
            <tvdb>200023</tvdb>
            <content>episode</content>
        </meta>
        <link>https://apicdn.vip/drive/index.php?id=%2FGUCeTf1MxLPwQiUFX%2F0dA14knh8OQ0wjcQI7HA3dzlyeUPUijW8M9q9wBPH0KFxAn1cEGUzm4GCRQFMra26l57voTDlYryaA8RfGZTpb032scetkOUMlc0D1s%2FeZg4L7T8zQPbQZftCzhuDN34pLz&ref=&res=default</link>
    </item>

    <item>
        <title>4x10.Asylum</title>
        <meta>
            <tvdb>200024</tvdb>
            <content>episode</content>
        </meta>
        <link>https://apicdn.vip/drive/index.php?id=63zfnhBBI4h0SDYG3RrC2AUmwUWmqVq0QRj%2BKuqjV35in7x1VJ3lC92g9iSr2xCMaXZkfkzh9k%2B%2FWRWzbBvUXmSnwsNBCVoyvMqYvrKQ%2Bk%2Bu%2FnhAP2PRqqg3Ob%2FueD0xO1wCTB7SShbAj1AEvbbvi6&ref=&res=default</link>
    </item>

    <item>
        <title>4x11.California Reich</title>
        <meta>
            <tvdb>200025</tvdb>
            <content>episode</content>
        </meta>
        <link>https://apicdn.vip/drive/index.php?id=1Zbdq1J7VX9D7S63RzHjiQdUhamob%2BOLvBwdJTBMfsyVpf8nL%2BtB5S%2BLHUxO29l9Cu5EJ7AXpgJbAd97KYB8S1Tdektwj87wV%2BlCXXo4PHx7J89FotBdmcTWAPmnTdvDAvD0R8bm5gUgK6xVRxtS0d&ref=&res=default</link>
    </item>

    <item>
        <title>4x12.The Dying Fields</title>
        <meta>
            <tvdb>200026</tvdb>
            <content>episode</content>
        </meta>
        <link>https://apicdn.vip/drive/index.php?id=LQopTDNvUktq0t9YmpmPqAvtB866MOz8rjrA5O6DocY%2B3GJPO2sTtYsBvCHuX6pNZhrOAMI1I%2FFQmAfqxn0r33IIPyuTo4G2Du9iIhJj2OivbhcVQijATqKjasZ5PATUHZVy5G1cYywu1OmpEOBctr&ref=&res=default</link>
    </item>

    <item>
        <title>4x13.Lipschitz Live!</title>
        <meta>
            <tvdb>200027</tvdb>
            <content>episode</content>
        </meta>
        <link>https://apicdn.vip/drive/index.php?id=IlNFbL18zqAkdW5vwHcHuA0KvqbWnI9nI3HwCatDy2xCc6CC17SUJ378ZYee%2BymErYoEWq0evkS0qQZC%2Btpew%2FHX98%2Bds8ZOusGORlqdkPBwDx3s8rfwPHKnzmuDOgCDeGgnnBNcemgmUz7Akf7a%2F6&ref=&res=default</link>
    </item>

    <item>
        <title>4x14.Mother and Child</title>
        <meta>
            <tvdb>200028</tvdb>
            <content>episode</content>
        </meta>
        <link>https://apicdn.vip/drive/index.php?id=88mhBWoNTUQ3GhAZux7OSAAdLBSHa0M08gYKbAHKIRtUuL8yYRtt6OmSwEGrcyjdsn0Kqbv12eoYECghExq1Rax0E8JOVjo6Ig6IW3MASscNTDefw6OUp80dLAW3gfw80R49beTrnunf9XqA%2B4G6o2&ref=&res=default</link>
    </item>

    <item>
        <title>4x15.Net Worth</title>
        <meta>
            <tvdb>200029</tvdb>
            <content>episode</content>
        </meta>
        <link>https://apicdn.vip/drive/index.php?id=4KFRpJQ%2FX23ocE2f7X6G4wZwRXWPVZ%2F5hc1C7W%2B2FB7m7m5JsjMjFQcmrf1HCqIJqlfokMZ0blBAC%2FYvfuGqthPNNwb2Ya52C7y0fjr455PpFp9QWuAdHdVeeOQNqoZxBZtVHFp%2FdMJl0W8z5NzZZl&ref=&res=default</link>
    </item>

    <item>
        <title>4x16.Slide by Wire</title>
        <meta>
            <tvdb>200030</tvdb>
            <content>episode</content>
        </meta>
        <link>https://apicdn.vip/drive/index.php?id=8rA62xfjJ4P4JDv9Lc1zjwh6oj8yXFloUe5NyUp9KXakWUWi2lkU6thLNzJ8MrIZtwHdQ3WXxHfFb79ulcErM1EJetg3v88W2vVMnT4ndIO0JLC1snU%2BskLKgu3D2CUfGa16hDEnklNaTVdCzc82hp&ref=&res=default</link>
    </item>

    <item>
        <title>4x17.Data World</title>
        <meta>
            <tvdb>200031</tvdb>
            <content>episode</content>
        </meta>
        <link>https://apicdn.vip/drive/index.php?id=nKBL%2BGskbK2ssuWq2cpvOA2FPrSH2kN9iysQVCfpkmGf3sg4XkYPuwbUpqXLEtmkxzEXkk6AX%2BEd6u8fNPnHpBo62uyfylPm2tllLy1qeV4TEVwURDQtDoL2cKluXdNnj%2FdNx83TewaNHXCIdj1cOQ&ref=&res=default</link>
    </item>

    <item>
        <title>4x18.Way Out West</title>
        <meta>
            <tvdb>200032</tvdb>
            <content>episode</content>
        </meta>
        <link>https://apicdn.vip/drive/index.php?id=M0dK8qOPDswmwBcUX2sNPQxTQK7uB6q0OD1E6WD%2Fru9fcZ3fLLPzPHS66A8WHjfyhk3iddJDNaHLKZizN4pPE8jWU50KvyJwzG8Z77vcfsNIpf5k5clwCJaQuIRTk64NHKNNZ4am7aNIfuWn4cLvBS&ref=&res=default</link>
    </item>

    <item>
        <title>4x19.My Brother's Keeper</title>
        <meta>
            <tvdb>200033</tvdb>
            <content>episode</content>
        </meta>
        <link>https://apicdn.vip/drive/index.php?id=Q5WJ08TlTHH5ihoqx%2B5kDQ4KROMOHnbBmPQIe%2Fqunhty1DGBgjsRox7h3zn7fZpHp%2FGrhxjEL%2FGyZWaS0rzNMbjs6g%2B4kpMimldeNkrf5BySB0NwDohCsBYnWQ57lrbchSwzbGkJkTbed34pqCDrtK&ref=&res=default</link>
    </item>

    <item>
        <title>4x20.The Chasm</title>
        <meta>
            <tvdb>200034</tvdb>
            <content>episode</content>
        </meta>
        <link>https://apicdn.vip/drive/index.php?id=1FzA4UeFhXM78NKvFAqGbAhqJNc62ZDieq7ol3MQ%2F3%2F3p27MalCcZUkjGpekxNdwwGDPnAZzBr2Et7lalu8Qjx4buE7TiK5ENavzia%2FThZSO7p%2FeljGDevdcnXjHPWdi0GlpUuY6FjSn31UYEXnxKr&ref=&res=default</link>
    </item>

    <item>
        <title>4x21.Roads Taken</title>
        <meta>
            <tvdb>200035</tvdb>
            <content>episode</content>
        </meta>
        <link></link>
    </item>

    <item>
        <title>4x22.Revelations</title>
        <meta>
            <tvdb>200036</tvdb>
            <content>episode</content>
        </meta>
        <link>https://apicdn.vip/drive/index.php?id=ljD6YFrq%2BwX6cWQcWJyErQjZUTjyJK6JRqX4X1xOhYAGvYOLng1TYYvSL8XX53Lw66aoeE8rmUDtf1fYFvu0l4%2BLMjJJIaCTxhel8ib%2FaVyMvV4yTxzkKAs219t9A7W6ZGjv2pob%2BYcF%2BqyLmEqKDH&ref=&res=default</link>
    </item>
</xml>