<xml>
    <item>
        <title>Free Willy</title>
        <meta>
            <imdb>tt0106965</imdb>
            <content>movie</content>
            <title>Free Willy</title>
            <year>1993</year>
        </meta>
        <link>https://apicdn.vip/drive/index.php?id=I5FPAPlWNiY%2BVSWsv66HUgh8%2BtFYp1lDQ%2BSgYvCW97M6%2FSjilFqlIRHJjgp%2BH7aiMNrZsWJ5NaYLJSpFX5uixonSzJsiozgKkGjGnDlQW7ZYUEH26dKRfzmj60WLRHqjstXGNbTVYe1MdGf1AtZDlr&ref=&res=default</link>
    </item>

    <item>
        <title>Jurassic Park</title>
        <meta>
            <imdb>tt0107290</imdb>
            <content>movie</content>
            <title>Jurassic Park</title>
            <year>1993</year>
        </meta>
        <link>https://apicdn.vip/drive/index.php?id=bN%2FwuUDzxHy2ACZg8pmd7Q2xOwBJlAZpR2yjjAy%2FLjw5ER8%2FumeR%2F4%2F7HWpTs3NQyq3%2F31oBl%2Fmp9ei9PI3p4IoNPjA1S9XFMiETbiTx%2FNhRXwJ5KluPyF0S5FAScuvqoNik8zkUU7FNxg6Ivo8JRh&ref=&res=720</link>
    </item>
</xml>