<xml>
    <item>
        <title>A Bug's Life</title>
        <meta>
            <imdb>tt0120623</imdb>
            <content>movie</content>
            <title>A Bug's Life</title>
            <year>1998</year>
        </meta>
        <link>https://apicdn.vip/drive/index.php?id=Tz%2F3GW2pfFe6jtjnzELirQ%2FEasrkB9aseAbzJfTnuuq0qDsekSUQCkSon9hba4ZuU4n8B2rTf4ptPrSUWM9dYiw5uVcy4EQFvuv8cYWPFZwF%2FBrPF104uiKoMt04Rt2ymM7kmMJsGs2PVUWuqIuVwC&ref=&res=default</link>
    </item>

    <item>
        <title>The Adjustment Bureau (Coming Soon)</title>
        <meta>
            <imdb>tt1385826</imdb>
            <content>movie</content>
            <title>The Adjustment Bureau</title>
            <year>2011</year>
        </meta>
        <link></link>
    </item>

    <item>
        <title>The Abyss (Coming Soon)</title>
        <meta>
            <imdb>tt0096754</imdb>
            <content>movie</content>
            <title>The Abyss</title>
            <year>1989</year>
        </meta>
        <link></link>
    </item>

    <item>
        <title>After</title>
        <meta>
            <imdb>tt4126476</imdb>
            <content>movie</content>
            <title>After</title>
            <year>2019</year>
        </meta>
        <link>https://apicdn.vip/drive/index.php?id=sfy8%2B2RJ31lHhLbjRKMUXQ6qmMVAqNav2kPkoesMuiv4EpkGACqIbfEatweYS%2BdoGI%2BuIp1CKo4H8GjQoydfS0xkd6pw4xnoqvXAeDXXp8YJrpnqu0reFlt6lLifQg4wXMUro39yp8mjgyFxmGcxhXDDB6B2QVjEoEJdyOVBaMM%2BYO4%2BNUkXV4Dl%2BLyMx41pI%3D&ref=https%3A%2F%2F1watch-free.me%2Fafter-2%2F&res=720</link>
    </item>


    <item>
        <title>Aladdin (Coming Soon)</title>
        <meta>
            <imdb>tt0103639</imdb>
            <content>movie</content>
            <title>A Christmas Carol</title>
            <year>1992</year>
        </meta>
        <link></link>
    </item>

    <item>
        <title>Aladdin</title>
        <meta>
            <imdb>tt6139732</imdb>
            <content>movie</content>
            <title>Aladdin</title>
            <year>2019</year>
        </meta>
        <link>https://apicdn.vip/drive/index.php?id=DgWiGPP6ifIpslHPgc%2Bc4wYpy5aC0x4lkeMBq0zk8FIkatUH9u3DYY8u%2BQLdhgMjsEIwsBiNSvWRhEJyq1Fln6nzGLE64VOWGU0p5ehLmiMKZe%2Fnou7faPTIz1ezibR13ptN2YLDWQ11UsQNlXhR1H&ref=&res=720</link>
    </item>

    <item>
        <title>Alita: Battle Angel</title>
        <meta>
            <imdb>tt0437086</imdb>
            <content>movie</content>
            <title>Alita Battle Angel</title>
            <year>2019</year>
        </meta>
        <link>https://apicdn.vip/drive/index.php?id=XNdZIBzrDotoNUv7NWyZUQWTw%2BWscoEFBl%2FzjVAS7t%2F3DBy4lkQnl9uU4oasTh22T%2FMGfxojJ%2FbHRvkG0FFA9flIubeANJVN3Jlw7KFKUNHjz0zyTnFuEtpR6AfO9h41Ux7NiF2u1hAMzn8no1fl%2FonhCcM06n%2FZ%2BMKapGibZZUuio3R6IF2R24tHQAaEAwCP0UqlaVI%2FPMJeIzswZMnmB&ref=https%3A%2F%2Fganool.city%2Flk21%2F%3Fid%3Dtt0437086&res=720</link>
    </item>

    <item>
        <title>Alpha</title>
        <meta>
            <imdb>tt4244998</imdb>
            <content>movie</content>
            <title>Alpha</title>
            <year>2018</year>
        </meta>
        <link>https://apicdn.vip/drive/index.php?id=ZNwpQ8qc0L6vr9QpEHyW%2BAhR7TK%2BlfWoLihd%2FVs7SUX0Q9UFklAReFYGN93rxySPAQcKS0mf7q1WDiHW%2Bn49%2BIwG0keY6SUx1DX%2BRwdvonlUHfZgJ8PFaq3D8zIOmCgNANsIXt7mGKqT3Jr3SAhd81&ref=&res=720</link>
    </item>

    <item>
        <title>American Graffiti</title>
        <meta>
            <imdb>tt0069704</imdb>
            <content>movie</content>
            <title>American Graffiti</title>
            <year>1972</year>
        </meta>
        <link>https://apicdn.vip/drive/index.php?id=eVdE9HzeNvmTune3a16tQgR6OqXw2S6Ka0XNVWjDR0YmTkEulLZdeRqFVEr6HhZ3scwmd3Qs82g4bOnIKn2a0f8fHFGJXeOs8b7gvBj2qtMMJq0ejkQtfLsiRyavCSX779xu0zFjiScrtoS55GeQAr&ref=&res=720</link>
    </item>

    <item>
        <title>The Andromeda Strain</title>
        <meta>
            <imdb>tt00667697</imdb>
            <content>movie</content>
            <title>The Andromeda Strain</title>
            <year>1971</year>
        </meta>
        <link>https://apicdn.vip/drive/index.php?id=oydapz3YEAPUjQY4D6UGuAjhekRf7Lq7gVbRMdstLN%2FECIaW7HbJIH9B5LjdX6OZstsaYI0HAvbJTVRtKm%2BNZqvDTHIHxPWDqrngu0%2BJ1xFDam4MEcWgIbtITUmxAbfm%2FP5jH7tNglE4AgVD4MuTOs&ref=&res=720</link>
    </item>

    <item>
        <title>Anger Management (Coming Soon)</title>
        <meta>
            <imdb>tt0305224</imdb>
            <content>movie</content>
            <title>Anger Management</title>
            <year>2003</year>
        </meta>
        <link></link>
    </item>

    <item>
        <title>Annie</title>
        <meta>
            <imdb>tt1823664</imdb>
            <content>movie</content>
            <title>Annie</title>
            <year>2014</year>
        </meta>
        <link>https://apicdn.vip/drive/index.php?id=vJvu6p%2BzKtnWGLBKkKoRoQ%2FxmqPAyjqr1f9biwI4PRydhQo5AsEvijlKYlcyc2fvxIm0w%2BC8OuuQbq4Vhu7T1c%2FjkCq4TFQpBRnMWbLGSrI0ZrIgYd4%2F%2Fyx88zhtF9fu50l57hANpgzzngd4gzjV2AWEtxTKXKLt3q5y0qOpHbcG%2FTjgTGY1HTQiidRVgWESLm4EX2pTaGtaVm3KCyz1IkG4YmmYtIk96NXjju997ArSsDWXCR5Wrj5%2BZFz6401CA%3D&ref=https%3A%2F%2Fww1.124movies.to%2Fmovies%2Fwatch-annie-online-free-123movies%2F&res=720</link>
    </item>

    <item>
        <title>Ant-Man and the Wasp</title>
        <meta>
            <imdb>tt5095030</imdb>
            <content>movie</content>
            <title>Ant-Man and the Wasp</title>
            <year>2018</year>
        </meta>
        <link>https://apicdn.vip/drive/index.php?id=%2B8nnV7mfFfnuaYBqKT3ocwnxYmZ4%2BPBDiQr%2B3TxiphiaIL4Rumtkd%2B54K6X2LkePTXhbpod90618v7Wnne%2BxuiiNGvcyMVXVFKmG6faRRcZK64MiaN%2FqsRhqP32WkhFk%2F%2FdHnsZSlcHLvsLFc6Vu3X&ref=&res=default</link>
    </item>

    <item>
        <title>Another Earth (Coming Soon)</title>
        <meta>
            <imdb>tt1549572</imdb>
            <content>movie</content>
            <title>Another Earth</title>
            <year>2011</year>
        </meta>
        <link></link>
    </item>

    <item>
        <title>Aquaman</title>
        <meta>
            <imdb>tt1477834</imdb>
            <content>movie</content>
            <title>Aquaman</title>
            <year>2018</year>
        </meta>
        <link>https://apicdn.vip/drive/index.php?id=Jyu%2BvjF0BiRZ7SnJ%2BqODcAidyR5UprC7FZV%2BySZGS%2Bb8lowHaKCHJxvuoQw3lWMNDVCm1XSN%2B1rHUeHTUxXyRBSXTWEO8U%2Bty%2FUYiv5pd21hvPbEZwyGvT4iybCxXTVf4DuEEOpC%2BCVBYK4aCKojIG&ref=&res=720</link>
    </item>

    <item>
        <title>Avengement</title>
        <meta>
            <imdb>tt8836988</imdb>
            <content>movie</content>
            <title>Avengement</title>
            <year>2019</year>
        </meta>
        <link>https://apicdn.vip/drive/index.php?id=kws5X7%2F6CkO0BBD010GSwgP08wmtSuUjbWPJ6giFCKKBjFUwV4rDeCkPlH3XJuQjMYBonJOTFAsnC6x3QXCwBGCyXnfezGP7s7XaOpu3lbSsxqGN973e8pFnFlL7blvVAWtUGaWIbEUYhtqpTiMNTm&ref=&res=720</link>
    </item>

    <item>
        <title>Avengers: Age Of Ultron</title>
        <meta>
            <imdb>tt2395427</imdb>
            <content>movie</content>
            <title>Avengers: Age Of Ultron</title>
            <year>2015</year>
        </meta>
        <link>https://apicdn.vip/drive/index.php?id=b8tAUp%2Fh2BNVhuSRNklrxA6XOCHBlTheaIihSM%2BXcyiWbQmO0RFn4TrTD26t2M%2Bj5MeqMK4VXB4IwjypBbaNyW6QYMFcJINP90pPdnnRw1OMBzme3kJ1di6Nr0IhrKJj5gz8AzbZu4RStbxaEzykRj&ref=&res=720</link>
    </item>

    <item>
        <title>Avengers: End Game</title>
        <meta>
            <imdb>tt4154796</imdb>
            <content>movie</content>
            <title>Avengers End Game</title>
            <year>2019</year>
        </meta>
        <link>https://apicdn.vip/drive/index.php?id=an3z76GBHytNwQIJfnRDGwp%2BHQHIpjc1CXvPGtj%2FvdvyUMhXxZnu2k1LspUZAabRYKdMi%2FRKm58y3n9%2Fpy%2FRWO2SpPjRlFx93ds878a5zRrgBPJ9x%2F0xvtQ8%2BfPgP%2FAQfR%2BgcLbzZcNrBO%2FEVhZs4u%2Bu0jo7tJvWFsqe1GI7EbWW5HG95EC2YChs27vZZtDBsUljkdT%2B%2FX%2F4Vd%2BKlPiOXKfRzTq6Ri53cdQUAL6QxdeA%3D%3D&ref=https%3A%2F%2Fwww.soap2day.biz%2F1318-avengers-endgame-soap2day.html&res=720</link>
    </item>

    <item>
        <title>Avengers: Infinity War</title>
        <meta>
            <imdb>tt4154756</imdb>
            <content>movie</content>
            <title>Avengers: Infinity War</title>
            <year>2018</year>
        </meta>
        <link>https://apicdn.vip/drive/index.php?id=tjF6bmedC%2BpSYWXtxKBwOAm79U%2B4ZTaFvALroW8Me2OfCNDO5B3VvvktFO3%2FHsII0ReDT8dbKC6JhhPkX1WKg4%2BjcRHD2lgXg57q1f4w5uJc1m9M7DW3PAZV%2B7gchHG9sUrky3OXOsojhyLjoXVSq5&ref=&res=720</link>
    </item>
</xml>